setnext_ai/__init__.py
setnext_ai/metering.py
setnext_ai_metering-1.0.0.dist-info/METADATA
setnext_ai_metering-1.0.0.dist-info/WHEEL
setnext_ai_metering-1.0.0.dist-info/licenses/LICENSE
setnext_ai_metering-1.0.0.dist-info/RECORD
