Metadata-Version: 2.3
Name: setnext_ai_metering
Version: 1.0.0
Summary: Metering Initial Package
Project-URL: Homepage, https://setnext.io
Project-URL: Issues, https://setnext.io/issues
Author-email: Nithyanantha Babu <nithyanantha@setnext.ai>
License-File: LICENSE
Classifier: License :: OSI Approved :: MIT License
Classifier: Operating System :: OS Independent
Classifier: Programming Language :: Python :: 3
Requires-Python: >=3.8
Requires-Dist: anthropic
Requires-Dist: httpx
Requires-Dist: pytz
